MANIFEST.in
README.md
pyproject.toml
setup.py
src/controllogger/__init__.py
src/controllogger/__version__
src/controllogger.egg-info/PKG-INFO
src/controllogger.egg-info/SOURCES.txt
src/controllogger.egg-info/dependency_links.txt
src/controllogger.egg-info/not-zip-safe
src/controllogger.egg-info/top_level.txt
src/controllogger/enums/__init__.py
src/controllogger/enums/log_levels.py
src/controllogger/enums/logger_event.py
src/controllogger/enums/operator.py
src/controllogger/enums/terminal_out_file.py
src/controllogger/handler/__init__.py
src/controllogger/handler/base.py
src/controllogger/handler/db_log_handler.py
src/controllogger/handler/python_console_handler.py
src/controllogger/handler/rich_console_handler.py
src/controllogger/handler/tar_rotating_file_handler.py
src/controllogger/logger/__init__.py
src/controllogger/logger/base.py
src/controllogger/logger/base_easy.py
src/controllogger/logger/control.py
src/controllogger/logger/input.py
src/controllogger/logger/output.py
src/controllogger/misc/__init__.py
src/controllogger/misc/base_dataclass.py
src/controllogger/misc/base_logger_config.py
src/controllogger/misc/context.py
src/controllogger/misc/easy_logger.py
src/controllogger/misc/easy_logger_config.py
src/controllogger/misc/filter.py
src/controllogger/misc/get_rich_console.py
src/controllogger/misc/input_logger_config.py
src/controllogger/misc/last_resort.py
src/controllogger/misc/log_function_config.py
src/controllogger/misc/logger_class.py
src/controllogger/misc/logger_defaults_config.py
src/controllogger/misc/output_logger_config.py
src/controllogger/misc/pydantic_logger_class.py
src/controllogger/misc/singleton.py
src/controllogger/misc/snake_case.py
src/controllogger/misc/wrapper.py
src/controllogger/models/__init__.py
src/controllogger/models/log.py