Metadata-Version: 2.1
Name: controllogger
Version: 0.2.9.19
Summary: A simple and easy to use logger for python.
Author-email: Julius König <info@bastelquartier.de>
License: GPL-3.0
Keywords: logger,control,controllogger,fastapi,rich,logging,log,logs,context,contextlogger,loggers,logging-framework,logging-library,logging-tool,logging-utility,logging-util
Classifier: Development Status :: 3 - Alpha
Classifier: Intended Audience :: Developers
Classifier: License :: OSI Approved :: GNU General Public License v3 (GPLv3)
Classifier: Programming Language :: Python :: 3
Classifier: Programming Language :: Python :: 3 :: Only
Classifier: Programming Language :: Python :: 3.7
Classifier: Programming Language :: Python :: 3.8
Classifier: Programming Language :: Python :: 3.9
Classifier: Programming Language :: Python :: 3.10
Classifier: Programming Language :: Python :: 3.11
Classifier: Topic :: Software Development :: Libraries :: Python Modules
